torss/__init__.py
torss/app.py
torss/args.py
torss/feed.py
torss/feeds/__init__.py
torss/feeds/economist.py
torss/feeds/gov_pl_gis.py
torss/feeds/wiki_current_events.py
torss/utils.py
rss_scrap-0.3.0.dist-info/METADATA
rss_scrap-0.3.0.dist-info/WHEEL
rss_scrap-0.3.0.dist-info/entry_points.txt
rss_scrap-0.3.0.dist-info/RECORD
