Metadata-Version: 2.1
Name: rss-scrap
Version: 0.3.0
Summary: Web scrapper which converts sites to RSS feeds.
Home-page: https://git.goral.net.pl/rss-scrap.git/about
License: GPL-3.0-only
Author: Michal Goral
Author-email: dev@goral.net.pl
Requires-Python: >=3.8,<4.0
Classifier: License :: OSI Approved :: GNU General Public License v3 (GPLv3)
Classifier: Programming Language :: Python :: 3
Classifier: Programming Language :: Python :: 3.8
Classifier: Programming Language :: Python :: 3.9
Classifier: Programming Language :: Python :: 3.10
Classifier: Programming Language :: Python :: 3.11
Requires-Dist: aiohttp (>=3.8.3,<4.0.0)
Requires-Dist: beautifulsoup4 (>=4.9.0,<5.0.0)
Project-URL: Repository, https://git.goral.net.pl/rss-scrap.git
